<order>
    <details>
        <quantity>612</quantity>
        <bracket>612</bracket>
        <stock>(S30) Standard Smooth</stock>
        <foil>false</foil>
    </details>
    <fronts>
        <card>
            <id>1-iV-kq8A3onQuNmup7w7lMQpG1SSMuba</id>
            <slots>0,1,2</slots>
            <name>Mana Drain (Raymond Swanland).jpg</name>
            <query>mana drain</query>
        </card>
        <card>
            <id>1U0T8cVKlegIGald4MSkd3QScWYY08EUy</id>
            <slots>3,4,5</slots>
            <name>Mana Geyser (NormalPlus Martina Pilcerova).jpg</name>
            <query>mana geyser</query>
        </card>
        <card>
            <id>1SnNdgMqFi4WB0ii5flNwypBNZy0SLwKD</id>
            <slots>6,7,8,9</slots>
            <name>Mana Vault.png</name>
            <query>mana vault</query>
        </card>
        <card>
            <id>1_D3Gho_dbYhRMI2tJfIXEwOiSUUZwyN6</id>
            <slots>10,11,12,13,14,15,16,17,18,19</slots>
            <name>Maze of Ith (Normal) [DMR] {250}.jpg</name>
            <query>maze of ith</query>
        </card>
        <card>
            <id>1Q_uYAF_x-vHoBaBuCVstbKQKVuaHjrXy</id>
            <slots>20,21,22,23</slots>
            <name>Midnight Clock.png</name>
            <query>midnight clock</query>
        </card>
        <card>
            <id>1tvxIcq3XGgHJ0HS57TqEWeBb3AXcpIg2</id>
            <slots>24,25,26,27</slots>
            <name>Mikokoro, Center of the Sea.png</name>
            <query>mikokoro center of sea</query>
        </card>
        <card>
            <id>1MpMsGPnptVn-p4-MYoUr3dfh-Uba_n83</id>
            <slots>28,29,30,31,32,33,34,35,36</slots>
            <name>Minamo, School at Water's Edge (Borderless Stephen Stark).jpg</name>
            <query>minamo school at waters edge</query>
        </card>
        <card>
            <id>1XqZa7jeNyR6OgFhJCfHjCulKa_ZLddDX</id>
            <slots>37,38,39,40,41,42</slots>
            <name>Mirrorweave.png</name>
            <query>mirrorweave</query>
        </card>
        <card>
            <id>1mH42FZeNCBeK68kAkNrl334CRhimT8e9</id>
            <slots>43,44,45</slots>
            <name>Misleading Signpost.png</name>
            <query>misleading signpost</query>
        </card>
        <card>
            <id>1RoBQoZIo9lI_UNLrhy90dOdfj39T7fg7</id>
            <slots>46,47,48,49</slots>
            <name>Mystic Reflection (Extended YW Tang).jpg</name>
            <query>mystic reflection</query>
        </card>
        <card>
            <id>124RqxsLflT1S9AwZMdYzGlWy3y1_FSlx</id>
            <slots>50,51,52,53,54,55,56,57,58,59</slots>
            <name>Mystic Remora (Kelogsloops) [SLD] {406}.jpg</name>
            <query>mystic remora</query>
        </card>
        <card>
            <id>1zV_ib6rfZCv22_5JT98ENn10ymNlzGCC</id>
            <slots>60,61,62,63,64</slots>
            <name>Mystic Sanctuary (Randy Vargas).png</name>
            <query>mystic sanctuary</query>
        </card>
        <card>
            <id>1nGRyATb2Cr3rDrKr5Ro1Ff9tdtwKjX6b</id>
            <slots>65,66,67,68,69,70</slots>
            <name>Narset's Reversal (Viktor Titov).png</name>
            <query>narsets reversal</query>
        </card>
        <card>
            <id>1vG8r6-hlyM_ucyUZGvz4fHex7fwqep5f</id>
            <slots>71,72,73</slots>
            <name>Nature's Lore (Julie Dillon).png</name>
            <query>natures lore</query>
        </card>
        <card>
            <id>1kWAxzTy2RvY8z7NcMEyTW35NzxM4Is_q</id>
            <slots>74,75</slots>
            <name>Necropotence.png</name>
            <query>necropotence</query>
        </card>
        <card>
            <id>1jmG5RSYw5eHcTu7lDbPoYYPzENnyFtfK</id>
            <slots>76,77</slots>
            <name>Neheb, the Eternal.jpg</name>
            <query>neheb eternal</query>
        </card>
        <card>
            <id>1oK4IpEQmiteN1au5BUSabyDkrR7-G89n</id>
            <slots>78,79,80,81</slots>
            <name>Nissa, Who Shakes the World.png</name>
            <query>nissa who shakes world</query>
        </card>
        <card>
            <id>15-ZPd_dawgss1-yV06G7hSJzxGB2Kyr3</id>
            <slots>82,83,84,85,86,87,88,89</slots>
            <name>Notion Thief.png</name>
            <query>notion thief</query>
        </card>
        <card>
            <id>1L_sqfahxidh1iPoHwh7noX0JzZCma1wl</id>
            <slots>90,91,92,93,94,95,96,97,98,99</slots>
            <name>Nykthos, Shrine to Nyx.png</name>
            <query>nykthos shrine to nyx</query>
        </card>
        <card>
            <id>1sxF2GTMpq3adJiqq1yNLnwbp-iRbX_km</id>
            <slots>100,101,102,103,104,105</slots>
            <name>Nyxbloom Ancient (Filip Burburan).png</name>
            <query>nyxbloom ancient</query>
        </card>
        <card>
            <id>1ip9SdqID2fF4MJYWwCP_iZEI17L20nVV</id>
            <slots>106,107,108,109</slots>
            <name>Oboro, Palace in the Clouds.png</name>
            <query>oboro palace in clouds</query>
        </card>
        <card>
            <id>1baB2IaypYBvcUn6IFoB3Ych3hBodq7_d</id>
            <slots>110,111,112,113,114</slots>
            <name>Obscuring Haze.jpg</name>
            <query>obscuring haze</query>
        </card>
        <card>
            <id>1fxsxuih53LR958v1GLDTdJdVC7TUZXwe</id>
            <slots>115,116,117,118</slots>
            <name>Ojer Taq, Deepest Foundation (Normal) [LCI] {26} (1).jpg</name>
            <query>ojer taq deepest foundation</query>
        </card>
        <card>
            <id>1ovhOXTt8qrrhO_6k0UwvHCz4mFx5g2GS</id>
            <slots>119,120,121,122</slots>
            <name>Okina, Temple to the Grandfathers.png</name>
            <query>okina temple to grandfathers</query>
        </card>
        <card>
            <id>14XCEZAodUFn-bq_ulKaMbv968DUsoUfu</id>
            <slots>123,124,125,126</slots>
            <name>Omniscience.png</name>
            <query>omniscience</query>
        </card>
        <card>
            <id>1ZtOChx2xRgsNzeoc1EQJOMrKzSx0cX0S</id>
            <slots>127,128</slots>
            <name>Ondu Inversion (Extended James Paick).jpg</name>
            <query>ondu inversion</query>
        </card>
        <card>
            <id>1uE-vgdhAJE-7dPRpVWrDHCEMyt6KncQT</id>
            <slots>129,130,131,132</slots>
            <name>Open the Way (Livia Prima).png</name>
            <query>open way</query>
        </card>
        <card>
            <id>1yu4wMIuAQSIiH26VhEinE5ACKNzbrV5D</id>
            <slots>133,134,135,136,137,138</slots>
            <name>Oracle of Mul Daya (Vance Kovacs).png</name>
            <query>oracle of mul daya</query>
        </card>
        <card>
            <id>1s5vIMAojHj3454SQEOu-h6jF5xfMYEBr</id>
            <slots>139,140,141,142,143,144,145,146</slots>
            <name>Orcish Bowmasters.png</name>
            <query>orcish bowmasters</query>
        </card>
        <card>
            <id>11lNf4aG4Mc_d5ZgiHplXcpxpu8FHBwhC</id>
            <slots>147,148,149,150,151,152,153,154,155,156</slots>
            <name>Otawara, Soaring City (Borderless Yuta Shimpo).jpg</name>
            <query>otawara soaring city</query>
        </card>
        <card>
            <id>1XxoZ6YEjUPdisFTf50AI1RYi8hzb1UNg</id>
            <slots>157,158,159,160,161,162,163,164</slots>
            <name>Phyrexian Arena (NormalPlus Martina Fackova).jpg</name>
            <query>phyrexian arena</query>
        </card>
        <card>
            <id>1vUeKpWBl3idvV3-pWtP6AC9bwU-x1xBq</id>
            <slots>165,166,167,168</slots>
            <name>Phyrexian Reclamation.png</name>
            <query>phyrexian reclamation</query>
        </card>
        <card>
            <id>1T6Usw25UeF_KSqGK9oa0iAt1VB8zrvAZ</id>
            <slots>169,170,171,172,173,174,175,176,177,178</slots>
            <name>Phyrexian Tower [MH3] {303}.jpg</name>
            <query>phyrexian tower</query>
        </card>
        <card>
            <id>1DEDPK0KLDU_Siw-TGuoH8fS7Tr5yufiL</id>
            <slots>179,180,181,182</slots>
            <name>Pitiless Plunderer [SPG] {5}.jpg</name>
            <query>pitiless plunderer</query>
        </card>
        <card>
            <id>14FgsMECDsA9dGUrL-FPg-0-Akfu6TmQY</id>
            <slots>183,184,185,186</slots>
            <name>Planar Nexus.png</name>
            <query>planar nexus</query>
        </card>
        <card>
            <id>1sQeobgoIvBxscikp3Mhc8kCK1TH7Mk4i</id>
            <slots>187,188,189,190,191</slots>
            <name>Prismatic Vista.png</name>
            <query>prismatic vista</query>
        </card>
        <card>
            <id>1AqOL5twGQvbTSiPiOymoRgOZa-eJLmD_</id>
            <slots>192,193,194,195</slots>
            <name>Ragavan, Nimble Pilferer.jpg</name>
            <query>ragavan nimble pilferer</query>
        </card>
        <card>
            <id>1qc4Uff2jyS9Q7bBylTNJNVuYBzWXnwrc</id>
            <slots>196,197,198,199,200,201</slots>
            <name>Raise the Palisade (Jason Kang).png</name>
            <query>raise palisade</query>
        </card>
        <card>
            <id>17-T1LNdEXZVeF2eILe4Wvw3DH-KFCE-K</id>
            <slots>202,203,204,205</slots>
            <name>Rakdos, Patron of Chaos (Normal) [MKM] {224}.jpg</name>
            <query>rakdos patron of chaos</query>
        </card>
        <card>
            <id>1qAsAnJVUxE8g72ODjQSfysyvZ7x1MI2v</id>
            <slots>206,207,208,209</slots>
            <name>Razaketh, the Foulblooded.png</name>
            <query>razaketh foulblooded</query>
        </card>
        <card>
            <id>1lu7BTBzeUyN9mb1XiPlCz30zFTT0Bnxx</id>
            <slots>210,211,212,213</slots>
            <name>Reanimate (OTP).jpg</name>
            <query>reanimate</query>
        </card>
        <card>
            <id>1XUc2YWFGhemw_Xf42s-2C3J-5sDTt28R</id>
            <slots>214,215,216,217,218,219</slots>
            <name>Reconnaissance (Normal) [EXO] {17}.jpg</name>
            <query>reconnaissance</query>
        </card>
        <card>
            <id>1mL5kYvIaAJ0SACkWs4YB-pXgRfmD-K10</id>
            <slots>220,221,222,223,224</slots>
            <name>Reflecting Pool (Alayna Danner).png</name>
            <query>reflecting pool</query>
        </card>
        <card>
            <id>1UjXGJXBhdiLEXuL7wXkUS4GHar90_eqn</id>
            <slots>225,226,227,228</slots>
            <name>Reliquary Tower.png</name>
            <query>reliquary tower</query>
        </card>
        <card>
            <id>1tEVfFPR2zQl5kNOwQX5Wd_i1HMPKB2GB</id>
            <slots>229,230,231,232</slots>
            <name>Revel in Riches (Eric Deschamps).png</name>
            <query>revel in riches</query>
        </card>
        <card>
            <id>1YcB9ae_T7MpKKTEcDqg2Me1XzCmZPM7t</id>
            <slots>233,234,235,236</slots>
            <name>Reya Dawnbringer.png</name>
            <query>reya dawnbringer</query>
        </card>
        <card>
            <id>1v9_cMFKGR4PAgTmoYBiyZrd0dvGreihB</id>
            <slots>237,238,239,240,241,242,243,244,245,246</slots>
            <name>Roaming Throne (Normal) [LCI] {258}.jpg</name>
            <query>roaming throne</query>
        </card>
        <card>
            <id>1QJqO6x7OXcdGYdwfZJxiHZDMmJ8nUyXk</id>
            <slots>247,248,249,250</slots>
            <name>Runaway Steam-Kin.png</name>
            <query>runaway steam kin</query>
        </card>
        <card>
            <id>1hkmLTK_yBeV6raDiq4gcvCarQslXjQ6e</id>
            <slots>251,252,253,254</slots>
            <name>Sakura-Tribe Elder (Carl Critchlow).png</name>
            <query>sakura tribe elder</query>
        </card>
        <card>
            <id>1pSgeeXdZXVA57qdj3cD3xAZQ4QNwDbI3</id>
            <slots>255,256,257,258</slots>
            <name>Scarblade Elite.png</name>
            <query>scarblade elite</query>
        </card>
        <card>
            <id>1xxyFcBrguHavlo9WfZGlXYbhso3bSQKo</id>
            <slots>259,260,261,262,263,264,265,266</slots>
            <name>Seedborn Muse.png</name>
            <query>seedborn muse</query>
        </card>
        <card>
            <id>1QmxRiP8A_NCtIntK_Ql8YOmELPfysByM</id>
            <slots>267,268,269,270</slots>
            <name>Serra the Benevolent.png</name>
            <query>serra benevolent</query>
        </card>
        <card>
            <id>19aGjpHmd1d3jkOtcgzn1INyndIFPr3hj</id>
            <slots>271,272,273,274</slots>
            <name>Serra's Emissary.jpg</name>
            <query>serras emissary</query>
        </card>
        <card>
            <id>1rg51rl4RxyLA-3YoFcLtNRLGzkSRENOq</id>
            <slots>275,276,277,278</slots>
            <name>Serra's Sanctum (Ancient Ciruelo).png</name>
            <query>serras sanctum</query>
        </card>
        <card>
            <id>189Z7gz-sMiB8cCcR2x22N2gtk6H9WW6w</id>
            <slots>279,280,281,282</slots>
            <name>Settle the Wreckage.png</name>
            <query>settle wreckage</query>
        </card>
        <card>
            <id>1H9wcQLReUUviNwVFOBlrii1Rp-_CDOsg</id>
            <slots>283,284,285,286</slots>
            <name>Shadowspear (Yeong Hao Han).png</name>
            <query>shadowspear</query>
        </card>
        <card>
            <id>1O2R-XLfClTmuGI861TfXvogx89D-2kuS</id>
            <slots>287,288,289</slots>
            <name>Shinka, the Bloodsoaked Keep (NormalPlus Thomas M. Baxa).jpg</name>
            <query>shinka bloodsoaked keep</query>
        </card>
        <card>
            <id>1z_549JWkY_avjICtYwTebfzNoZaXLIDB</id>
            <slots>290,291,292,293,294,295,296,297</slots>
            <name>Shizo, Death's Storehouse (John Matson).png</name>
            <query>shizo deaths storehouse</query>
        </card>
        <card>
            <id>1vFyh4dKmGu41ZlayJs51HrZEuBwswLNc</id>
            <slots>298,299,300,301</slots>
            <name>Silence (Modern Wayne Reynolds).png</name>
            <query>silence</query>
        </card>
        <card>
            <id>11GMe-WqJuC7x_kMKA_yMOVZMNj3OOGNq</id>
            <slots>302,303,304,305</slots>
            <name>Skullbriar the Walking Grave.jpg</name>
            <query>skullbriar walking grave</query>
        </card>
        <card>
            <id>1ajBQi9GtALxPH51-kajI8D83M8oVzcX9</id>
            <slots>306,307,308,309,310,311</slots>
            <name>Skullclamp.png</name>
            <query>skullclamp</query>
        </card>
        <card>
            <id>1qcQsIag88M3aT6Wqm1J7-bb4VUqEYrIS</id>
            <slots>312,313,314,315,316,317,318,319,320,321,322,323,324,325</slots>
            <name>Skyclave Relic (Daniel Ljunggren).jpg</name>
            <query>skyclave relic</query>
        </card>
        <card>
            <id>1U9I3rY8ASUt1FkADl7G-8_FSYY7T4Fri</id>
            <slots>326,327,328,329</slots>
            <name>Skyshroud Claim.png</name>
            <query>skyshroud claim</query>
        </card>
        <card>
            <id>1M3qBov6dmIKA4-mK2ItHf32WMcyZcZI8</id>
            <slots>330,331,332,333,334,335</slots>
            <name>Smothering Tithe (Enchanting Tales) [WOT] {13}.jpg</name>
            <query>smothering tithe</query>
        </card>
        <card>
            <id>1fh224H1toZn3n3IjxRDy9eTumF-gmy30</id>
            <slots>336,337,338</slots>
            <name>Sokenzan, Crucible of Defiance.png</name>
            <query>sokenzan crucible of defiance</query>
        </card>
        <card>
            <id>1i9DNNfbahk3pRJkdJawJVHobkW5Is59l</id>
            <slots>339,340</slots>
            <name>Sting, the Glinting Dagger (Borderless Nino Is).jpg</name>
            <query>sting glinting dagger</query>
        </card>
        <card>
            <id>1bR3znvtSnMHrDrWatua2VqySoYkqfCM2</id>
            <slots>341,342,343,344</slots>
            <name>Storm-Kiln Artist.jpg</name>
            <query>storm kiln artist</query>
        </card>
        <card>
            <id>1dEHs3aeSqkYsAgjS_F2JJbJjpX6qeYOV</id>
            <slots>345,346,347,348,349,350,351,352,353,354</slots>
            <name>Strip Mine.png</name>
            <query>strip mine</query>
        </card>
        <card>
            <id>13O9WES_SA340HqOKdMCa9EZKaol_XQBG</id>
            <slots>355,356,357</slots>
            <name>Sudden Spoiling.png</name>
            <query>sudden spoiling</query>
        </card>
        <card>
            <id>1oM539Hodr8m-abm3oTJbQg4_D4rTTOIZ</id>
            <slots>358,359,360,361</slots>
            <name>Sunforger.png</name>
            <query>sunforger</query>
        </card>
        <card>
            <id>1Fl2WJc-Mb66j3dcnpMj_orAV7sLYfDMT</id>
            <slots>362,363,364,365,366,367</slots>
            <name>Swiftfoot Boots.png</name>
            <query>swiftfoot boots</query>
        </card>
        <card>
            <id>1lHeRCEySNwlsxvR2IczHBH8VBfEKX8eA</id>
            <slots>368,369,370,371</slots>
            <name>Sword of Feast and Famine (Borderless Thomas M. Baxa).jpg</name>
            <query>sword of feast and famine</query>
        </card>
        <card>
            <id>1OioVxxyxFVlZ4uPDDWjcCFFITxsDFTj1</id>
            <slots>372,373,374,375,376,377</slots>
            <name>Sword of Feast and Famine.png</name>
            <query>sword of feast and famine</query>
        </card>
        <card>
            <id>1BsU4Q5hFgiiKvg3ktXmXKYu6MY5bRJrQ</id>
            <slots>378,379,380,381,382,383,384,385,386,387</slots>
            <name>Sword of Hearth and Home.jpg</name>
            <query>sword of hearth and home</query>
        </card>
        <card>
            <id>1Ah74rhf6Se7RvpV-NjX-GMI7Hx3Zyy4u</id>
            <slots>388,389,390,391,392,393,394,395,396,397</slots>
            <name>Sword of the Animist (Daniel Ljunggren).png</name>
            <query>sword of animist</query>
        </card>
        <card>
            <id>1zH13vg3txcNVJXBmQq6sAI309wRvW_jG</id>
            <slots>398,399,400,401</slots>
            <name>Sylvan Library (Bryan Sola).png</name>
            <query>sylvan library</query>
        </card>
        <card>
            <id>1T14EYG7nG4sbNPCcl9EDgzdNOXy7JcDj</id>
            <slots>402,403</slots>
            <name>Tainted Strike (Modern James Ryman).jpg</name>
            <query>tainted strike</query>
        </card>
        <card>
            <id>1ez-IWFKScKo6sQDb2B5kTMySnOUMKy0I</id>
            <slots>404,405,406,407,408,409</slots>
            <name>Takenuma, Abandoned Mire.jpg</name>
            <query>takenuma abandoned mire</query>
        </card>
        <card>
            <id>1z9baZ0fDKQKwTLjgeoTnyOO6r2ohBfDx</id>
            <slots>410,411,412,413</slots>
            <name>Tangle.png</name>
            <query>tangle</query>
        </card>
        <card>
            <id>1Y1Khd46trjGZbkQgNOE0Y0pVWPEvlZjc</id>
            <slots>414,415,416,417,418,419,420,421,422,423,424,425,426,427,428</slots>
            <name>Teferi's Protection [SLD] {1691}.jpg</name>
            <query>teferis protection</query>
        </card>
        <card>
            <id>1JhilyJnQ69VDQVrYal6upySM_hAH5UcD</id>
            <slots>429,430,431,432</slots>
            <name>Tempt with Discovery.png</name>
            <query>tempt with discovery</query>
        </card>
        <card>
            <id>1pWo_y9mUWwVzKncmTfiOuZzAi9WCURN4</id>
            <slots>433,434,435,436</slots>
            <name>Terror of the Peaks (Andrey Kuzinskiy).png</name>
            <query>terror of peaks</query>
        </card>
        <card>
            <id>10CGc1uH_rOFr8Z9vhpF8rcOf2BTw8g3r</id>
            <slots>437,438,439,440</slots>
            <name>The Black Gate (Marc Simonetti).png</name>
            <query>black gate</query>
        </card>
        <card>
            <id>1tJsBZ3MGRegk4SKp_3D9OCCjLbaAgg96</id>
            <slots>441,442,443,444,445,446,447,448,449,450,451,452</slots>
            <name>The One Ring (Veli Nyström).png</name>
            <query>one ring</query>
        </card>
        <card>
            <id>1fthyNXKkHVo2ooJmEJgXrBZAHZML9qFe</id>
            <slots>453,454,455,456,457,458,459,460</slots>
            <name>The Ozolith (Sam Burley).jpg</name>
            <query>ozolith</query>
        </card>
        <card>
            <id>1b55RcPOGmLk5cemKsJ2zjmABMCp1iqFQ</id>
            <slots>461,462,463</slots>
            <name>The Reality Chip.png</name>
            <query>reality chip</query>
        </card>
        <card>
            <id>1hMSYsVaxdRsRDDaxApmKd-HSyb4StHCY</id>
            <slots>464,465,466,467</slots>
            <name>The World Tree.png</name>
            <query>world tree</query>
        </card>
        <card>
            <id>1hRh_QI8q2gpHCgZPpJJPnUnG9c1-jVdf</id>
            <slots>468,469,470,471</slots>
            <name>Thespian_s Stage.png</name>
            <query>thespians stage</query>
        </card>
        <card>
            <id>1Ph34Ug_C5OMlG0_OCPoeb1wo0Tr8NUse</id>
            <slots>472,473,474,475,476</slots>
            <name>Thought Vessel (rk post).png</name>
            <query>thought vessel</query>
        </card>
        <card>
            <id>1u9KAlHb4aNlGbtnBkMFMU-OEF07JVFxX</id>
            <slots>477,478,479</slots>
            <name>Time Stop.png</name>
            <query>time stop</query>
        </card>
        <card>
            <id>1O0TnI6oyxLDjGqqmWCbxWuD8hUp2qGME</id>
            <slots>480,481,482,483,484,485</slots>
            <name>Tolarian Academy.png</name>
            <query>tolarian academy</query>
        </card>
        <card>
            <id>1JIuN4vP320gRe0soGU4s6mJLAgc5Ul6L</id>
            <slots>486,487,488</slots>
            <name>Toski, Bearer of Secrets (Jason Rainville).jpg</name>
            <query>toski bearer of secrets</query>
        </card>
        <card>
            <id>1pRcFkiTxggwjsyncvQj7lYF1lkMnRUpf</id>
            <slots>489,490,491,492</slots>
            <name>Toxic Deluge.png</name>
            <query>toxic deluge</query>
        </card>
        <card>
            <id>18DmF2HppglFBM5xi91kvjPf6g4dshkJW</id>
            <slots>493,494,495,496,497</slots>
            <name>Treasure Vault (Normal, Universes Beyond) [PIP] {314}.jpg</name>
            <query>treasure vault</query>
        </card>
        <card>
            <id>1i7pfzAAtw6ge3hVVup8JaaqhsbnJE6OZ</id>
            <slots>498,499,500,501</slots>
            <name>Tree of Perdition.png</name>
            <query>tree of perdition</query>
        </card>
        <card>
            <id>19p1l3_KkW5tQqnNiP_IPGTQ_J0jhMqer</id>
            <slots>502,503,504,505</slots>
            <name>Ugin, the Spirit Dragon.png</name>
            <query>ugin spirit dragon</query>
        </card>
        <card>
            <id>1KfqZLb0ka482e0n23YHU6vasTXjs5n7r</id>
            <slots>506,507,508,509</slots>
            <name>Umezawa's Jitte (Normal) [BOK] {163}.jpg</name>
            <query>umezawas jitte</query>
        </card>
        <card>
            <id>1N8nrfE8uQUszpQeZmajE2VxF_8Rnxz5S</id>
            <slots>510,511,512,513</slots>
            <name>Underworld Breach.png</name>
            <query>underworld breach</query>
        </card>
        <card>
            <id>10qPBCohh8JuQ1OTDt6G85JAQQ6bZigMi</id>
            <slots>514,515,516,517</slots>
            <name>Unwinding Clock.png</name>
            <query>unwinding clock</query>
        </card>
        <card>
            <id>1aQJd2tvZSkKWknyuZFMUOQAc8QJmwWpQ</id>
            <slots>518,519,520,521,522,523,524,525,526,527</slots>
            <name>Urborg, Tomb of Yawgmoth.png</name>
            <query>urborg tomb of yawgmoth</query>
        </card>
        <card>
            <id>1Dk6CryIjCmURt3ThinKaXohJZ_hpsm9t</id>
            <slots>528,529,530,531,532,533,534,535,536,537,538,539</slots>
            <name>Urza's Saga (Titus Lunter).jpg</name>
            <query>urzas saga</query>
        </card>
        <card>
            <id>1PEjNdy4oIsfLhFPZwP5okg0vic4dWsNX</id>
            <slots>540,541,542,543</slots>
            <name>Urza, Lord High Artificer.png</name>
            <query>urza lord high artificer</query>
        </card>
        <card>
            <id>1yCL_98yVAm3b0yIFrlRDJMAxD_46ucKk</id>
            <slots>544,545,546,547</slots>
            <name>Valakut, the Molten Pinnacle.png</name>
            <query>valakut molten pinnacle</query>
        </card>
        <card>
            <id>166uvOde7Xt7HRA3YBrYFvBMBRMRLP8fl</id>
            <slots>548,549,550,551</slots>
            <name>Vein Ripper (Normal) [MKM] {110}.jpg</name>
            <query>vein ripper</query>
        </card>
        <card>
            <id>1k1K_Q7pEDIp14ice0QICEgRftKIzm5zH</id>
            <slots>552,553,554,555,556,557,558,559,560,561</slots>
            <name>Vesuva (Sketch Zoltan Boros &amp; Gabor Szikszai).jpg</name>
            <query>vesuva</query>
        </card>
        <card>
            <id>1RLFaBMU-KrZR-6waEt9_Aj_P9_Vu8-PE</id>
            <slots>562,563,564,565</slots>
            <name>Vilis, Broker of Blood.png</name>
            <query>vilis broker of blood</query>
        </card>
        <card>
            <id>1wpAbz2TpHSfTb9xnhUzGB1D88RpKA740</id>
            <slots>566,567,568,569</slots>
            <name>Virtus the Veiled.png</name>
            <query>virtus veiled</query>
        </card>
        <card>
            <id>1IknxSyGvece5nW_A_pcc63pOGuf8qz46</id>
            <slots>570</slots>
            <name>War Room (Milivoj Ceran).jpg</name>
            <query>war room</query>
        </card>
        <card>
            <id>1l1UpcxMc24TXcAdV8TPuN5lf2ggNhhG1</id>
            <slots>571,572,573,574</slots>
            <name>Wheel of Fortune.png</name>
            <query>wheel of fortune</query>
        </card>
        <card>
            <id>1RIlvOut37UWfLk1xug2bktUUv_BmAEZN</id>
            <slots>575,576,577,578</slots>
            <name>Whip of Erebos.jpeg</name>
            <query>whip of erebos</query>
        </card>
        <card>
            <id>18xWmk_3BLikXFoagGHzH_70GxoEbUzUx</id>
            <slots>579,580,581,582</slots>
            <name>Whispersilk Cloak (Daren Bader).png</name>
            <query>whispersilk cloak</query>
        </card>
        <card>
            <id>1ueHWL6cilJZ76I-12lNWtJgvUkA7bkrR</id>
            <slots>583,584,585,586,587,588,589,590,591,592</slots>
            <name>Winding Canyons (Ancient John Avon).jpg</name>
            <query>winding canyons</query>
        </card>
        <card>
            <id>18hQ9W_amLDSfUKmFHrJln0Mx7VM17YqN</id>
            <slots>593,594,595,596</slots>
            <name>Winged Boots.png</name>
            <query>winged boots</query>
        </card>
        <card>
            <id>1UyuOyya1Hgeejqt4XgWA4fTMJslg6Pv7</id>
            <slots>597,598,599,600,601,602,603,604,605,606</slots>
            <name>Worn Powerstone (Henry G. Higgenbotham).png</name>
            <query>worn powerstone</query>
        </card>
        <card>
            <id>1pAhr1I7FfdLi23N2SIG6SdiZJ53htBc0</id>
            <slots>607,608,609,610,611</slots>
            <name>Yavimaya, Cradle of Growth.jpg</name>
            <query>yavimaya cradle of growth</query>
        </card>
    </fronts>
    <backs>
        <card>
            <id>16_hA1aTFxYTLTH-1z-ipcRgjMPDEvnwf</id>
            <slots>115,116,117,118</slots>
            <name>Temple of Civilization (b).png</name>
            <query>temple of civilization</query>
        </card>
        <card>
            <id>1mESAgb0oFLa9n1B6oX9Hycmb5AsEuK4z</id>
            <slots>127,128</slots>
            <name>Ondu Skyruins (James Paick).png</name>
            <query>ondu skyruins</query>
        </card>
    </backs>
    <cardback>1Aa98sI-YvFUSnNYGGfJvc7NR9VtUOpNp</cardback>
</order>